[
    {
        "ID": "7d588660",
        "Time": "2025-10-16 21:00:00",
        "Description": "Study Bible And Pray",
        "Priority": "High",
        "Tag": "WORSHIP",
        "Email": "okeyobinna2001@gmail.com"
    },
    {
        "ID": "9d30d4ab",
        "Time": "2025-10-16 21:00:00",
        "Description": "Study Bible And Pray",
        "Priority": "High",
        "Tag": "WORSHIP",
        "Email": "okeyobinna2001@gmail.com"
    },
    {
        "ID": "050e040e",
        "Time": "2025-10-16 21:00:00",
        "Description": "Study Bible And Pray",
        "Priority": "High",
        "Tag": "WORSHIP",
        "Email": "okeyobinna2001@gmail.com"
    }
]